strength_utils/__init__.py
strength_utils/formulas.py
strength_utils/models.py
strength_utils/percent_tables.py
strength_utils/planner.py
strength_utils/programs.py
strength_utils/progression.py
strength_utils/units.py
strength_utils/volume.py
strength_utils-0.1.0.dist-info/METADATA
strength_utils-0.1.0.dist-info/WHEEL
strength_utils-0.1.0.dist-info/entry_points.txt
strength_utils-0.1.0.dist-info/RECORD
