Metadata-Version: 2.4
Name: strength-utils
Version: 0.1.0
Summary: Typed utilities for strength training: 1RM estimates, RPE/RIR tables, volume, progression, and simple program planning.
Author-email: benjaminmcf <mcfaddenben7@gmail.com>
License: MIT
Keywords: 1RM,RPE,fitness,powerlifting,strength,training
Requires-Python: >=3.11
Provides-Extra: streamlit
Requires-Dist: streamlit>=1.50.0; extra == 'streamlit'
